{"Dk4VRnNZ/QlOuGb/yU+yPA==":"miles-morales-spider-man-dark-black-background-artwork-5k-8k-3840x2160-1902-2000x1125.png","xM9BdNQKbc9slhyStgHpuA==":"dark-background-computer-desktop-wallpaper-34145-2000x1031.jpg","wOS4+FK0Lx8mHIDexWo3CQ==":"j%2520c%2520highschool%2520karanja-1128x752.jpg","W1L/HjWGtLGDPaewfS97fA==":"mahatma%2520gandhi%2520uccha%2520madhyamik%2520vidhyalay%2520lohagaon_convert_jpg-1128x548.jpg","RrnRkUK99MNf0wTAw1NVfg==":"s%2520b%2520jain-1030x421.jpg","78bVU5JG580QDiVrLB9x3w==":"j%2520c%2520highschool%2520karanja-1128x752.jpeg","ZVuSh3FBRrUUsQuzcrltUA==":"j%2520c%2520highschool%2520karanja-1128x752.jpeg","OPG4l+/tIQq8E9ykQNsFew==":"web-1280x852.jpg","uvAjUU4TP2xaFDQxLKZB7w==":"web-1280x852.jpeg","f6igSX0tr7Et+UhjShlYOw==":"web-1-1280x852.jpeg","wyzJM55Rj142N4mdQPqLvw==":"web-2-1280x852.jpeg","3+GO1aO8VBDwF0WTnQEyuA==":"tushar%2520web%2520image-1279x1280.jpg","8WZET8tBglgoR3XSxD/jMw==":"tushar%2520web%2520image-1279x1280.jpeg","59FvV4w2QqRbxocxJbl8rA==":"tushar%2520web%2520image-1279x1280.jpeg","0pRZ6bG2OzhIpoX6UqWqBg==":"tt-2000x1333.png","M8yYR3Z0K0Lg+O1sKEWlHQ==":"tushar%2520web%2520image-1279x1280.jpeg","oyF5Gl4AK4pCAqdRfkO3tg==":"wfsff-1279x720.jpg","j5HP4v48FNNOlzEDIAlFMw==":"robo-1200x1600.jpeg","MBpsZ3p4/UpBDCNrTa6b6A==":"perform%2520sign%2520mangnitude%2520addition%2520and%2520show%2520result%2520on%2520led-1256x942.jpg","kAz+CIzTWfCW+l0P8tFiwQ==":"parallel%2520-463x689.jpeg","0ed2Slh8Uyy5k3HiaDAtGg==":"moset-1256x942.jpg","Mc5yN+i4ukphvKZ35j8MSg==":"2%2520bit%2520counter-1256x1068.jpeg","zJ6Zpf27kS3yeIVhdgaDtQ==":"tur-853x596.jpg","hY2CRHJSAyOgLyR1S0ay8Q==":"ir-960x1280.jpg","PJPOkehVA7N+l4AJBnMDPQ==":"ir-960x1280.jpeg","aegq8avh0M+S8vPMtF0+8A==":"screenshot%25202025-10-15%2520025150-605x857.png","KBjP4seRfmivTo1CBwNUTw==":"hack-923x1280.jpg","NXpYiAajSfDw5blNIa1kuw==":"hack-923x1280.jpeg","SUqoXHWdlhaWJcuJfEYAVQ==":"sports-646x867.jpeg","wkkBZn1cw19nFBJWemDJNg==":"tushar%2520web%2520image-96x96.jpg","NMDWbvwOxZYzu74fe8vvbA==":"whatsapp%2520image%25202025-10-15%2520at%252003.41.36_93b6ecff-96x213.jpeg","N+5dGQ7oOayK1KV63vrMJA==":"whatsapp%2520image%25202025-10-15%2520at%252003.41.36_93b6ecff-68x151.jpeg","AzfrsliwXC0+yQK41wAYMg==":"c5e03278-f834-4935-ba92-f2a9ecde28fc-92x92.png","fMTMjXItx9llPuKLaoH+hA==":"c5e03278-f834-4935-ba92-f2a9ecde28fc-1-92x92.png","4q3RPTD/CKrkAL6kd9Ancw==":"3201a74b-3f20-4684-97b2-abc6f2b8a4ab-218x218.png"}